quwiki/__init__.py
quwiki/filenode.py
quwiki/generator.py
quwiki/initializer.py
quwiki/sources/__init__.py
quwiki/sources/gdrive.py
quwiki/sources/git.py
quwiki/templates/__init__.py
quwiki/templates/light/__init__.py
quwiki-0.0.2.data/scripts/quwiki
quwiki-0.0.2.dist-info/DESCRIPTION.rst
quwiki-0.0.2.dist-info/METADATA
quwiki-0.0.2.dist-info/RECORD
quwiki-0.0.2.dist-info/WHEEL
quwiki-0.0.2.dist-info/metadata.json
quwiki-0.0.2.dist-info/top_level.txt
